paperetl/__init__.py
paperetl/database.py
paperetl/elastic.py
paperetl/factory.py
paperetl/filesystem.py
paperetl/sqlite.py
paperetl/table.py
paperetl/text.py
paperetl/file/__init__.py
paperetl/file/__main__.py
paperetl/file/arx.py
paperetl/file/csvf.py
paperetl/file/execute.py
paperetl/file/pdf.py
paperetl/file/pmb.py
paperetl/file/tei.py
paperetl/schema/__init__.py
paperetl/schema/article.py
paperetl-2.5.2.dist-info/LICENSE
paperetl-2.5.2.dist-info/METADATA
paperetl-2.5.2.dist-info/WHEEL
paperetl-2.5.2.dist-info/top_level.txt
paperetl-2.5.2.dist-info/RECORD
