Metadata-Version: 2.1
Name: paperetl
Version: 2.5.2
Summary: ETL processes for medical and scientific papers
Home-page: https://github.com/neuml/paperetl
Author: NeuML
License: Apache 2.0: http://www.apache.org/licenses/LICENSE-2.0
Project-URL: Documentation, https://github.com/neuml/paperetl
Project-URL: Issue Tracker, https://github.com/neuml/paperetl/issues
Project-URL: Source Code, https://github.com/neuml/paperetl
Keywords: etl parse medical scientific papers
Classifier: License :: OSI Approved :: Apache Software License
Classifier: Operating System :: OS Independent
Classifier: Programming Language :: Python :: 3
Classifier: Topic :: Software Development
Classifier: Topic :: Utilities
Requires-Python: >=3.10
License-File: LICENSE
Requires-Dist: beautifulsoup4 >=4.8.1
Requires-Dist: lxml >=4.5.0
Requires-Dist: nltk >=3.5
Requires-Dist: pandas >=1.1.0
Requires-Dist: python-dateutil >=2.8.1
Requires-Dist: PyYAML >=5.3
Requires-Dist: requests >=2.22.0
Provides-Extra: all
Requires-Dist: elasticsearch >=7.8.0 ; extra == 'all'
Provides-Extra: elasticsearch
Requires-Dist: elasticsearch >=7.8.0 ; extra == 'elasticsearch'
